eggwrap-1.0.0.dist-info/METADATA
eggwrap-1.0.0.dist-info/WHEEL
eggwrap.libs/libblas-bd8a282c.so.3
eggwrap.libs/libOsi-4b1fcad7.so.1
eggwrap.libs/libClp-026930f2.so.1
eggwrap.libs/libquadmath-1c3f8ec4.so.0
eggwrap.libs/libbz2-5e516f77.so.1.0
eggwrap.libs/liblapack-86b2c207.so.3
eggwrap.libs/libCbc-5830e229.so.3
eggwrap.libs/libCbcSolver-837c33ed.so.3
eggwrap.libs/libCoinUtils-0a53b2b1.so.3
eggwrap.libs/libCgl-04ea3366.so.1
eggwrap.libs/libOsiClp-9ce46c9a.so.1
eggwrap.libs/libgfortran-df5d6f8d.so.5
eggwrap/__init__.py
eggwrap/eggwrap.cpython-311-x86_64-linux-gnu.so
eggwrap-1.0.0.dist-info/RECORD
